fastcaddy/__init__.py
fastcaddy/_modidx.py
fastcaddy/core.py
fastcaddy-0.0.9.dist-info/licenses/LICENSE
fastcaddy-0.0.9.dist-info/METADATA
fastcaddy-0.0.9.dist-info/WHEEL
fastcaddy-0.0.9.dist-info/entry_points.txt
fastcaddy-0.0.9.dist-info/top_level.txt
fastcaddy-0.0.9.dist-info/RECORD
